omero_forms/__init__.py
omero_forms/apps.py
omero_forms/settings.py
omero_forms/urls.py
omero_forms/utils.py
omero_forms/views.py
omero_forms/static/forms/js/060b2710bdbbe3dfe48b.svg
omero_forms/static/forms/js/4692b9ec53fd5972caa2.ttf
omero_forms/static/forms/js/5be1347c682810f199c7.eot
omero_forms/static/forms/js/82b1212e45a2bc35dd73.woff
omero_forms/static/forms/js/be810be3a3e14c682a25.woff2
omero_forms/static/forms/js/bundle.js
omero_forms/static/forms/js/bundle.min.js
omero_forms/static/forms/js/designer.js
omero_forms/static/forms/js/designer.min.js
omero_forms/templates/forms/designer.html
omero_forms/templates/forms/forms_init.js.html
omero_forms-2.1.1.dist-info/METADATA
omero_forms-2.1.1.dist-info/WHEEL
omero_forms-2.1.1.dist-info/top_level.txt
omero_forms-2.1.1.dist-info/RECORD
