Metadata-Version: 2.4
Name: omero-forms
Version: 2.1.1
Summary: OMERO forms app for enhanced metadata input and provenance
Author: D.P.W. Russell
Author-email: "T.T. Luik" <cellularimaging@amsterdamumc.nl>
License-Expression: AGPL-3.0
Project-URL: Homepage, https://github.com/NL-BioImaging/OMERO.forms
Project-URL: Download, https://github.com/NL-BioImaging/OMERO.forms/archive/refs/tags/v{version}.tar.gz
Keywords: OMERO.web,forms,provenance,history
Classifier: Development Status :: 5 - Production/Stable
Classifier: Environment :: Web Environment
Classifier: Framework :: Django
Classifier: Intended Audience :: End Users/Desktop
Classifier: Intended Audience :: Science/Research
Classifier: Natural Language :: English
Classifier: Operating System :: OS Independent
Classifier: Programming Language :: JavaScript
Classifier: Programming Language :: Python :: 3
Classifier: Topic :: Internet :: WWW/HTTP
Classifier: Topic :: Internet :: WWW/HTTP :: Dynamic Content
Classifier: Topic :: Internet :: WWW/HTTP :: WSGI
Classifier: Topic :: Scientific/Engineering :: Visualization
Classifier: Topic :: Software Development :: Libraries :: Application Frameworks
Classifier: Topic :: Text Processing :: Markup :: HTML
Requires-Python: >=3.9
Requires-Dist: omero-web>=5.6.0
Requires-Dist: Django<4.3,>=4.2.3
